simple_openapi_client/__init__.py
simple_openapi_client/config.py
simple_openapi_client/maker.py
simple_openapi_client/openapi/__init__.py
simple_openapi_client/openapi/document.py
simple_openapi_client/openapi/info.py
simple_openapi_client/openapi/path.py
simple_openapi_client/parser.py
simple_openapi_client/templates/async_client.jinja
simple_openapi_client/templates/async_method.jinja
simple_openapi_client/templates/client.jinja
simple_openapi_client/templates/method.jinja
simple_openapi_client-0.5.4.dist-info/METADATA
simple_openapi_client-0.5.4.dist-info/WHEEL
simple_openapi_client-0.5.4.dist-info/RECORD
