Metadata-Version: 2.1
Name: simple-openapi-client
Version: 0.5.4
Summary: OpenAPI Python client generator that follows the KISS principle.
Home-page: https://github.com/gacou54/openapi-client
License: BSD-3-Clause
Author: Gabriel Couture
Author-email: gacou54@gmail.ca
Requires-Python: >=3.8,<4.0
Classifier: License :: OSI Approved :: BSD License
Classifier: Programming Language :: Python :: 3
Classifier: Programming Language :: Python :: 3.8
Classifier: Programming Language :: Python :: 3.9
Classifier: Programming Language :: Python :: 3.10
Classifier: Programming Language :: Python :: 3.11
Classifier: Programming Language :: Python :: 3.12
Requires-Dist: Jinja2 (>=3.1.2,<4.0.0)
Requires-Dist: black (>=24.4.2,<25.0.0)
Requires-Dist: httpx (>=0,<1)
